MANIFEST.in
README.rst
setup.py
src/up/__init__.py
src/up/annotation.py
src/up/moods.py
src/up/sink.py
src/up/source.py
src/up/status.py
src/up/util.py
src/up.egg-info/PKG-INFO
src/up.egg-info/SOURCES.txt
src/up.egg-info/dependency_links.txt
src/up.egg-info/entry_points.txt
src/up.egg-info/requires.txt
src/up.egg-info/top_level.txt
src/up.egg-info/zip-safe
src/up_web/__init__.py
src/up_web/server.py
src/up_web/static/humans.txt
src/up_web/static/css/graphs.css
src/up_web/static/css/site.css
src/up_web/static/js/graphs.js
src/up_web/static/js/lava.js
src/up_web/templates/home.html
src/up_web/templates/lava.html
src/up_web/templates/core/base.html