Metadata-Version: 1.1
Name: up
Version: 0.2.1
Summary: Up - A next generation status monitor
Home-page: UNKNOWN
Author: Aaron Spaulding
Author-email: aaron@sachimp.com
License: UNKNOWN
Platform: UNKNOWN
Classifier: Programming Language :: Python
Classifier: Development Status :: 3 - Alpha
Classifier: Intended Audience :: Developers
Classifier: Intended Audience :: End Users/Desktop
Classifier: Programming Language :: Python :: 3.3
Classifier: Topic :: Internet :: WWW/HTTP
Classifier: Topic :: Office/Business
